omniclient/__init__.py
omniclient/omniclient.py
omniclient/s_cache.py
omniclient/s_cleanup.py
omniclient/s_config.py
omniclient/s_db.py
omniclient/s_log.py
omniclient/s_net.py
omniclient/s_util.py
omniclient-0.5.65679.dist-info/WHEEL
omniclient-0.5.65679.dist-info/METADATA
omniclient-0.5.65679.dist-info/RECORD
